MANIFEST.in
README.md
setup.py
resources/tiles/102x136/Back.png
resources/tiles/102x136/Blank.png
resources/tiles/102x136/Chun.png
resources/tiles/102x136/Front.png
resources/tiles/102x136/Haku.png
resources/tiles/102x136/Hatsu.png
resources/tiles/102x136/Man1.png
resources/tiles/102x136/Man2.png
resources/tiles/102x136/Man3.png
resources/tiles/102x136/Man4.png
resources/tiles/102x136/Man5-Dora.png
resources/tiles/102x136/Man5.png
resources/tiles/102x136/Man6.png
resources/tiles/102x136/Man7.png
resources/tiles/102x136/Man8.png
resources/tiles/102x136/Man9.png
resources/tiles/102x136/Nan.png
resources/tiles/102x136/Pei.png
resources/tiles/102x136/Pin1.png
resources/tiles/102x136/Pin2.png
resources/tiles/102x136/Pin3.png
resources/tiles/102x136/Pin4.png
resources/tiles/102x136/Pin5-Dora.png
resources/tiles/102x136/Pin5.png
resources/tiles/102x136/Pin6.png
resources/tiles/102x136/Pin7.png
resources/tiles/102x136/Pin8.png
resources/tiles/102x136/Pin9.png
resources/tiles/102x136/Shaa.png
resources/tiles/102x136/Sou1.png
resources/tiles/102x136/Sou2.png
resources/tiles/102x136/Sou3.png
resources/tiles/102x136/Sou4.png
resources/tiles/102x136/Sou5-Dora.png
resources/tiles/102x136/Sou5.png
resources/tiles/102x136/Sou6.png
resources/tiles/102x136/Sou7.png
resources/tiles/102x136/Sou8.png
resources/tiles/102x136/Sou9.png
resources/tiles/102x136/Ton.png
resources/tiles/51x68/Back.png
resources/tiles/51x68/Blank.png
resources/tiles/51x68/Chun.png
resources/tiles/51x68/Front.png
resources/tiles/51x68/Haku.png
resources/tiles/51x68/Hatsu.png
resources/tiles/51x68/Man1.png
resources/tiles/51x68/Man2.png
resources/tiles/51x68/Man3.png
resources/tiles/51x68/Man4.png
resources/tiles/51x68/Man5-Dora.png
resources/tiles/51x68/Man5.png
resources/tiles/51x68/Man6.png
resources/tiles/51x68/Man7.png
resources/tiles/51x68/Man8.png
resources/tiles/51x68/Man9.png
resources/tiles/51x68/Nan.png
resources/tiles/51x68/Pei.png
resources/tiles/51x68/Pin1.png
resources/tiles/51x68/Pin2.png
riichiroyale_cmiller548.egg-info/PKG-INFO
riichiroyale_cmiller548.egg-info/SOURCES.txt
riichiroyale_cmiller548.egg-info/dependency_links.txt
riichiroyale_cmiller548.egg-info/top_level.txt